tscope/__init__.py
tscope/_version.py
tscope/main.py
tscope/__pycache__/__init__.cpython-312.pyc
tscope/__pycache__/__init__.cpython-313.pyc
tscope/__pycache__/main.cpython-312.pyc
tscope/__pycache__/main.cpython-313.pyc
tscope-0.1.4.dist-info/licenses/LICENSE
tscope-0.1.4.dist-info/METADATA
tscope-0.1.4.dist-info/WHEEL
tscope-0.1.4.dist-info/top_level.txt
tscope-0.1.4.dist-info/RECORD
