Metadata-Version: 2.4
Name: tscope
Version: 0.1.4
Summary: A simple Python oscilloscope for displaying 1-dim dynamic data in the command line
Home-page: https://github.com/sszxc/TerminalScope
Author: Henrik
Author-email: Henrik <im.zhangxc@gmail.com>
Maintainer-email: Henrik <im.zhangxc@gmail.com>
License: MIT
Project-URL: Homepage, https://github.com/sszxc/TerminalScope
Project-URL: Issues, https://github.com/sszxc/TerminalScope/issues
Keywords: oscilloscope,terminal,visualization,real-time,data
Classifier: Development Status :: 3 - Alpha
Classifier: License :: OSI Approved :: MIT License
Classifier: Operating System :: OS Independent
Classifier: Topic :: Scientific/Engineering :: Visualization
Classifier: Topic :: Software Development :: Libraries :: Python Modules
Requires-Python: >=3.7
License-File: LICENSE
Dynamic: author
Dynamic: home-page
Dynamic: license-file
Dynamic: requires-python
